{
  "Application": {
    "cluster_name": "",
    "region": ""
  },
  "Auth-Server": {
    "client_id":"ea74e4f7-4042-4f5f-be8e-a8ccb31a11f6",
    "client_secret":"88CXlO74KW"
  },
  "APIs": {
    "catalog": {
      "protocol": "http",
      "service_name": "catalog-ms-quarkus-storefront-isv.itzroks-5500068atp-ottbmf-4b4a324f027aea19c5cbc0c3275c4656-0000.hkg02.containers.appdomain.cloud",
      "base_path": "/micro",
      "require": [
      ]
    },
    "orders": {
      "protocol": "http",
      "service_name": "orders-ms-quarkus-storefront-isv.itzroks-5500068atp-ottbmf-4b4a324f027aea19c5cbc0c3275c4656-0000.hkg02.containers.appdomain.cloud",
      "base_path": "/micro",
      "require": [
        "oauth"
      ]
    },
    "review": {
      "protocol": "http",
      "base_path": "/api",
      "require": [
        "oauth"
      ]
    },
    "customerService": {
      "protocol": "http",
      "service_name": "customer-ms-quarkus-storefront-isv.itzroks-5500068atp-ottbmf-4b4a324f027aea19c5cbc0c3275c4656-0000.hkg02.containers.appdomain.cloud",
      "base_path": "/micro",
      "paths": {
        "customer": "/customer"
      },
      "require": [
          "oauth"
      ],
      "redirect_url": "http://localhost"
    },
    "customer": {
      "protocol": "https",
      "service_name": "hpstorefront.verify.ibm.com",
      "base_path": "/v1.0/endpoint/default",
      "paths": {
        "userinfo": "/userinfo"
      },
      "require": [
        "oauth"
      ],
      "redirect_url": "http://localhost"
    },
    "otp": {
      "protocol": "https",
      "service_name": "hpstorefront.verify.ibm.com",
      "base_path": "/v2.0/factors/emailotp",
      "paths": {
        "generation": "/transient/verifications",
        "verify": "transient/verifications/"
      },
      "require": [
        "oauth"
      ],
      "redirect_url": "http://localhost"
    },
    "oauth20": {
      "protocol": "https",
      "service_name": "hpstorefront.verify.ibm.com",
      "base_path": "/v1.0/endpoint/default",
      "paths": {
        "authz": "/auth",
        "token": "/token"
      },
      "grant_types": [
        "password"
      ],
      "scopes": [
        "bluecompute"
      ],
      "redirect_url": "http://localhost"
    }
  }
}
